jsonprocess_progroveriman/__init__.py
jsonprocess_progroveriman-0.0.5.dist-info/LICENSE
jsonprocess_progroveriman-0.0.5.dist-info/METADATA
jsonprocess_progroveriman-0.0.5.dist-info/WHEEL
jsonprocess_progroveriman-0.0.5.dist-info/top_level.txt
jsonprocess_progroveriman-0.0.5.dist-info/RECORD
