Metadata-Version: 2.1
Name: jsonprocess-progroveriman
Version: 0.0.5
Summary: Some JSON process tools that I used regularly
Home-page: https://github.com/pypa/sampleproject
Author: Progroveriman
Author-email: xmk233@gmail.com
License: UNKNOWN
Platform: UNKNOWN
Classifier: Programming Language :: Python :: 3
Classifier: License :: OSI Approved :: MIT License
Classifier: Operating System :: OS Independent
Requires-Python: >=3.6
